include/cbor/arrays.h
include/cbor/bytestrings.h
include/cbor/callbacks.h
include/cbor/cbor_export.h
include/cbor/common.h
include/cbor/configuration.h
include/cbor/data.h
include/cbor/encoding.h
include/cbor/floats_ctrls.h
include/cbor/internal/builder_callbacks.h
include/cbor/internal/encoders.h
include/cbor/internal/loaders.h
include/cbor/internal/memory_utils.h
include/cbor/internal/stack.h
include/cbor/internal/unicode.h
include/cbor/ints.h
include/cbor/maps.h
include/cbor/serialization.h
include/cbor/streaming.h
include/cbor/strings.h
include/cbor/tags.h
include/cbor.h
include/cpp-base64/base64.h
include/rang.hpp
itk/Configuration/WebAssemblyInterfaceConfig.py
itk/Configuration/WebAssemblyInterface_snake_case.py
itk/WebAssemblyInterfacePython.py
itk/_WebAssemblyInterfacePython.so
itk/itkWasmImageIOPython.py
itk/itkWasmMeshIOPython.py
lib/cmake/libcbor/libcborConfig.cmake
lib/cmake/libcbor/libcborConfigVersion.cmake
lib/cmake/rang/rang-config-version.cmake
lib/cmake/rang/rang-config.cmake
lib/cmake/rang/rang-targets.cmake
lib/libcbor.a
lib/libcpp-base64.a
lib/pkgconfig/libcbor.pc
lib/pkgconfig/rang.pc
itk_webassemblyinterface-1.0b175.dist-info/METADATA
itk_webassemblyinterface-1.0b175.dist-info/WHEEL
itk_webassemblyinterface-1.0b175.dist-info/entry_points.txt
itk_webassemblyinterface-1.0b175.dist-info/licenses/LICENSE
itk_webassemblyinterface-1.0b175.dist-info/RECORD
